Workbook

Sheet Matriz Ckeck LIst
C3: MATRIZ PARA COMPROBACIÓN REQUERIMIENTOS DE CALIDAD DE PROYECTO ACADEMICO
D5: SISTEMA: | E5: SISTEMA DE GESTION DE ALICUOTAS
B7: Nº | C7: CRITERIOS DE CALIDAD (Documento/Requerimientos) | E7: Status Nivel de Acuerdo | F7: CU001 Administrar Sistema | G7: Status Nivel de Acuerdo | I7: CU002Gestionar Copropietarios | K7: CU003 Implementar Pagos
B9: 1 | C9: Agreed | E9: OK | F9: 1. Fue aprobado por la docente a cargo 2. Entrevista al Administrador del Condominio 3. Minuta realizada de la Entrevista | G9: OK | I9: 1. Aceptacion del docente y cliente | J9: OK | K9: 1. Fue aprobado por la docente a cargo 2. Entrevista al Administrador del Condominio 3. Minuta realizada de la Entrevista
B10: 2 | C10: Ranked | E10: NOK | F10: 1. En el SRS se especifíca que es un requisito Primario, pero los subcasos no poseen una priorización | G10: NOK | I10: 1.En el documento se especifica que es un requisito de tipo primario pero no se especifica que tipo de prioridad tienen | J10: NOK | K10: 1.En ninguna parte de la descripción de los casos de uso se especifica la prioridad (Alta, Media, Baja) o importancia del requisito.
B11: 3 | C11: Unambiguos | E11: OK | F11: 1. El requisito está redactado de forma clara 2. Cada miembro del equipo leyó el requisito y llegó a la misma interpretación | G11: OK | I11: 1. Se comenta en lo que consiste el requisito especificando actores, proposito, descripcion y tipo | J11: OK | K11: 1. Las precondiciones, postcondiciones y flujos están redactados paso a paso. 2. El tutor y el equipo interpretan de igual manera el caso de uso
B12: 4 | C12: Valid and up-to date | E12: OK | F12: 1. Se implementaron las correcciones realizadas por la docente 2. El SRS cuenta con control de versiones | G12: OK | I12: 1. Se tiene un sistema de versiones del SRS 2. Se implementarion cambios por recomendaciones del docente. | J12: OK | K12: 1. Cuenta con un control de versiones explícito 2. Incluye reglas de tiempo específicas y actualizadas
B13: 5 | C13: Correct | E13: OK | F13: 1. Se especifica de manera concreta cuales son los objetivos y las experctativas operativas | G13: OK | I13: 1. En la perspectiva del producto se deja en claro los objetivos que se esperan del producto. 2. Refleja lo que realmente necesita el stakeholder. | J13: OK | K13: 1. El flujo resuelve la necesidad real del sistema: el usuario reporta, el administrador audita, el sistema penaliza si hay mora y finalmente concilia emitiendo un comprobante.
B14: 6 | C14: Consistente | E14: OK | F14: 1. No se contradice dentro de su propio flujo y tampoco se contradice con otro requisito | G14: OK | I14: 1. EL documento se encuentra validado de ambiguedades, contradicciones y paradojas | J14: OK | K14: 1. Los casos de uso mantienen consistencia entre sí; los estados del pago fluyen lógicamente de un RF a otro sin contradecirse.
B15: 7 | C15: Verificable | E15: NOK | F15: 1. No existen criterios por los cuales se pueda medir el cumplimiento dado que no se implementó la propuesta. | G15: NOK | I15: 1. la medicion de su cumplimiento no es verificable por que no termino de ser implementado | J15: NOK | K15: 1. Requisito Medible 2. Faltan los Casos de Prueba explícitos o los criterios de aceptación medibles
B16: 8 | C16: Realizable | E16: NOK | F16: 1. Actualmente no es posible el desarrollo por falta de presupuesto y confirmación del cliente con la versión final del producto. | G16: NOK | I16: 1. actualmente el producto puede ser desarrollado con los costos especificados en la matriz de trazabilidad. 2. el producto no fue desarrollado. | J16: NOK | K16: 1.Las operaciones descritas son factibles con cualquier entorno de desarrollo actual. 2. No se ha desarrollado.
B17: 9 | C17: Traceable | E17: OK | F17: 1. El origen del requisito su relación con otros requisitos se evidencia de forma clara en la matriz de trazabilidad. | G17: OK | I17: 1. La relacion entre los requisitos esta especificada tanto en el docuemtno como de forma grafica en el diagrama de casos de uso | J17: OK | K17: 1. Tienen identificadores únicos jerárquicos 2. Las dependencias están claramente escritas
B18: 10 | C18: Complete | E18: OK | F18: 1. El requisito abarca todos los elementos relevantes y necesarios para asegurar su completitud. | G18: OK | I18: 1. Se aseguro de abarcar las necesidades que el stakeholder pidio | J18: OK | K18: 1. Contiene toda la información necesaria para entender y diseñar la función. 2. Describe completamente la funcionalidad esperada.
B19: 11 | C19: Understandability | E19: OK | F19: 1. El requisito es claro y comprensible para los involucrados, además el documento cuenta con un apartado de glosario de términos. | G19: OK | I19: 1. Se cuenta con un flujo normal por cada requerimiento que sirve como guia del como se usara y para que escenarios sirve | J19: OK | K19: 1. La sección de "Comentarios" en cada caso de uso aporta contexto de negocio que ayuda a cualquier desarrollador a entender el porqué de las reglas.

Sheet MODELO LISTA DE COMPROBACION - 
B1: SISTEMA: | C1: Sistema De Gestión De Alicuotas
B2: FECHA: | C2: 46126
B3: AUTOR: | C3: Jeancarlo Santi
B4: REQUERIMIENTOS EVALUADOS : | C4: CU001 Administrar Sistema
A6: CONTENIDO
A7: No. | B7: Pregunta | C7: SI | D7: NO
A8: 1 | B8: Todos los requerimientos relevantes se han documentado? | C8: X
A9: 2 | B9: Se han implementado las funciones requeridas? | C9: x
A10: 3 | B10: Existe algún mecanismo que permita seguir el impacto de dicho requerimiento a lo largo del resto de las actividades del ciclo productivo.? | C10: X
A11: 4 | B11: El origen de cada requerimento individual está claro ? | C11: X
A12: 5 | B12: Que tan facil es devolverse a los requerimientos? | C12: X
A13: 6 | B13: Los requerimientos reflejan las necesidades y deseos del cliente? | C13: X
A14: 7 | B14: No hay contradicciones entre los requerimientos? | C14: X
A15: 8 | B15: El requerimiento que se esta especificando contribuye a alcanzar un objetivo definido ? | C15: X
A16: 9 | B16: Existe un proceso acotado (en plazo y presupuesto) que permita determinar que el sistema construido satisface lo descrito en el propio requerimiento? | D16: X
A17: SUMATORIA: | C17: =COUNTA('MODELO LISTA DE COMPROBACION - '!$C$8:$C$16) -> 8 | D17: =COUNTA('MODELO LISTA DE COMPROBACION - '!$D$8:$D$16) -> 1
A18: PORCENTAJE : | C18: =C17/9 -> 0.88888889 | D18: =D17/9 -> 0.11111111
A20: DOCUMENTACIÓN
A21: No. | B21: Pregunta | C21: SI | D21: NO
A22: 1 | B22: Aplica un estandar para la documetación de requerimiento? | C22: X
A23: 2 | B23: Cumple con la estructura definida por el estandar? | C23: X
A24: 3 | B24: Utiliza un Glosario de términos normalizado? | C24: X
A25: 4 | B25: Los requerimientos Funcionales estan sujetos a una única interpretación? | C25: X
A26: 5 | B26: El modelo aplicado cumple con la sintaxis? | C26: X
A27: SUMATORIA: | C27: =COUNTA('MODELO LISTA DE COMPROBACION - '!$C$22:$C$26) -> 5 | D27: =COUNTA('MODELO LISTA DE COMPROBACION - '!$D$22:$D$26) -> 0
A28: PORCENTAJE : | C28: =C27/5 -> 1 | D28: =D27/5 -> 0
A30: NIVEL DE ACUERDO
A31: No. | B31: Pregunta | C31: SI | D31: NO
A32: 1 | B32: Todos los requerimientos han sido acordados con todos los interesados? | C32: X
A33: 2 | B33: Todos los requerimientos modificados han sido acordados por todos los implicados? | C33: X
A34: 3 | B34: Han sido resueltos todos los conflictos conocidos respectos de los requerimientos? | D34: X
A35: SUMATORIA: | C35: =COUNTA('MODELO LISTA DE COMPROBACION - '!$C$32:$C$34) -> 2 | D35: =COUNTA('MODELO LISTA DE COMPROBACION - '!$D$32:$D$34) -> 1
A36: PORCENTAJE : | C36: =C35/3 -> 0.66666667 | D36: =D35/3 -> 0.33333333
A40: RESUMEN
B41: CONTENIDO | C41: 89
B42: DOCUMENTACIÓN | C42: 100
B43: NIVEL DE ACUERDO | C43: 67

Sheet Hoja 1
B1: SISTEMA: | C1: Sistema De Gestión De Alicuotas
B2: FECHA: | C2: 46126
B3: AUTOR: | C3: Andres Cedeño
B4: REQUERIMIENTOS EVALUADOS : | C4: CU002Gestionar Copropietarios
A6: CONTENIDO
A7: No. | B7: Pregunta | C7: SI | D7: NO
A8: 1 | B8: Todos los requerimientos relevantes se han documentado? | C8: X
A9: 2 | B9: Se han implementado las funciones requeridas? | C9: X
A10: 3 | B10: Existe algún mecanismo que permita seguir el impacto de dicho requerimiento a lo largo del resto de las actividades del ciclo productivo.? | D10: X
A11: 4 | B11: El origen de cada requerimento individual está claro ? | C11: X
A12: 5 | B12: Que tan facil es devolverse a los requerimientos? | C12: X
A13: 6 | B13: Los requerimientos reflejan las necesidades y deseos del cliente? | C13: X
A14: 7 | B14: No hay contradicciones entre los requerimientos? | C14: X
A15: 8 | B15: El requerimiento que se esta especificando contribuye a alcanzar un objetivo definido ? | C15: X
A16: 9 | B16: Existe un proceso acotado (en plazo y presupuesto) que permita determinar que el sistema construido satisface lo descrito en el propio requerimiento? | D16: X
A17: SUMATORIA: | C17: =COUNTA('Hoja 1'!$C$8:$C$16) -> 7 | D17: =COUNTA('Hoja 1'!$D$8:$D$16) -> 2
A18: PORCENTAJE : | C18: =C17/9 -> 0.77777778 | D18: =D17/9 -> 0.22222222
A20: DOCUMENTACIÓN
A21: No. | B21: Pregunta | C21: SI | D21: NO
A22: 1 | B22: Aplica un estandar para la documetación de requerimiento? | C22: X
A23: 2 | B23: Cumple con la estructura definida por el estandar? | C23: X
A24: 3 | B24: Utiliza un Glosario de términos normalizado? | C24: X
A25: 4 | B25: Los requerimientos Funcionales estan sujetos a una única interpretación? | C25: X
A26: 5 | B26: El modelo aplicado cumple con la sintaxis? | C26: X
A27: SUMATORIA: | C27: =COUNTA('Hoja 1'!$C$22:$C$26) -> 5 | D27: =COUNTA('Hoja 1'!$D$22:$D$26) -> 0
A28: PORCENTAJE : | C28: =C27/5 -> 1 | D28: =D27/5 -> 0
A30: NIVEL DE ACUERDO
A31: No. | B31: Pregunta | C31: SI | D31: NO
A32: 1 | B32: Todos los requerimientos han sido acordados con todos los interesados? | C32: X
A33: 2 | B33: Todos los requerimientos modificados han sido acordados por todos los implicados? | C33: X
A34: 3 | B34: Han sido resueltos todos los conflictos conocidos respectos de los requerimientos? | C34: X
A35: SUMATORIA: | C35: =COUNTA('Hoja 1'!$C$32:$C$34) -> 3 | D35: =COUNTA('Hoja 1'!$D$32:$D$34) -> 0
A36: PORCENTAJE : | C36: =C35/3 -> 1 | D36: =D35/3 -> 0
A40: RESUMEN
B41: CONTENIDO | C41: 89
B42: DOCUMENTACIÓN | C42: 100
B43: NIVEL DE ACUERDO | C43: 100

Sheet Hoja 2
B1: SISTEMA: | C1: Sistema De Gestión De Alicuotas
B2: FECHA: | C2: 46126
B3: AUTOR: | C3: Tufiño Erick
B4: REQUERIMIENTOS EVALUADOS : | C4: CU003 Implementar Pagos
A6: CONTENIDO
A7: No. | B7: Pregunta | C7: SI | D7: NO
A8: 1 | B8: Todos los requerimientos relevantes se han documentado? | C8: X
A9: 2 | B9: Se han implementado las funciones requeridas? | C9: X
A10: 3 | B10: Existe algún mecanismo que permita seguir el impacto de dicho requerimiento a lo largo del resto de las actividades del ciclo productivo.? | C10: X
A11: 4 | B11: El origen de cada requerimento individual está claro ? | C11: X
A12: 5 | B12: Que tan facil es devolverse a los requerimientos? | C12: X
A13: 6 | B13: Los requerimientos reflejan las necesidades y deseos del cliente? | C13: X
A14: 7 | B14: No hay contradicciones entre los requerimientos? | C14: X
A15: 8 | B15: El requerimiento que se esta especificando contribuye a alcanzar un objetivo definido ? | C15: X
A16: 9 | B16: Existe un proceso acotado (en plazo y presupuesto) que permita determinar que el sistema construido satisface lo descrito en el propio requerimiento? | D16: X
A17: SUMATORIA: | C17: =COUNTA('Hoja 2'!$C$8:$C$16) -> 8 | D17: =COUNTA('Hoja 2'!$D$8:$D$16) -> 1
A18: PORCENTAJE : | C18: =C17/9 -> 0.88888889 | D18: =D17/9 -> 0.11111111
A20: DOCUMENTACIÓN
A21: No. | B21: Pregunta | C21: SI | D21: NO
A22: 1 | B22: Aplica un estandar para la documetación de requerimiento? | C22: X
A23: 2 | B23: Cumple con la estructura definida por el estandar? | C23: X
A24: 3 | B24: Utiliza un Glosario de términos normalizado? | C24: X
A25: 4 | B25: Los requerimientos Funcionales estan sujetos a una única interpretación? | C25: X
A26: 5 | B26: El modelo aplicado cumple con la sintaxis? | C26: X
A27: SUMATORIA: | C27: =COUNTA('Hoja 2'!$C$22:$C$26) -> 5 | D27: =COUNTA('Hoja 2'!$D$22:$D$26) -> 0
A28: PORCENTAJE : | C28: =C27/5 -> 1 | D28: =D27/5 -> 0
A30: NIVEL DE ACUERDO
A31: No. | B31: Pregunta | C31: SI | D31: NO
A32: 1 | B32: Todos los requerimientos han sido acordados con todos los interesados? | C32: X
A33: 2 | B33: Todos los requerimientos modificados han sido acordados por todos los implicados? | C33: X
A34: 3 | B34: Han sido resueltos todos los conflictos conocidos respectos de los requerimientos? | D34: X
A35: SUMATORIA: | C35: =COUNTA('Hoja 2'!$C$32:$C$34) -> 2 | D35: =COUNTA('Hoja 2'!$D$32:$D$34) -> 1
A36: PORCENTAJE : | C36: =C35/3 -> 0.66666667 | D36: =D35/3 -> 0.33333333
A40: RESUMEN
B41: CONTENIDO | C41: 89
B42: DOCUMENTACIÓN | C42: 100
B43: NIVEL DE ACUERDO | C43: 67

Sheet RECOMENDACIONES - CU001
A1: PREGUNTA | B1: RECOMENDACIÓN
A2: ¿Se ha definido una priorización explícita de los subcasos de uso dl requisito, indicando cuáles son obligatorios para la primera versión y cuáles pueden diferirse? | B2: Establecer una priorización formal para los subcasos CU-1.1 Iniciar Sesión, CU-1.2 Recuperar Contraseña y CU-1.3 Configurar Perfiles, usando un criterio uniforme como Must, Should, Could o prioridad Alta, Media, Baja.
A3: ¿Se han definido criterios de aceptación, resultados esperados y casos de prueba que permitan comprobar objetivamente el cumplimiento de los subcasos del requisito? | B3: Definir criterios de aceptación medibles para cada subcaso de uso del requisito . Estos criterios deben documentarse junto con casos de prueba funcionales y resultados esperados, de forma que el requisito pueda evaluarse objetivamente durante la fase de prueba.
A4: ¿El requisito es viable con los recursos, presupuesto, alcance y nivel de validación actual del proyecto? | B4: Revisar la factibilidad del requisito junto con el cliente y el equipo, delimitando una versión mínima viable. Si no existe presupuesto ni aprobación formal para toda la funcionalidad planteada, debe priorizarse una implementación mínima centrada en autenticación y acceso

Sheet RECOMENDACIONES - CU002
A1: PREGUNTA | B1: RECOMENDACIÓN
A2: ¿Se han validado y aprobado formalmente todos los entregables de la entrevista (videoconferencia, minuta, acta de aceptación)? | B2: Aplicar las debidas correcciones a la versión final y posteriormente validar con el cliente el documento, de preferencia debe constar la firma tanto del cliente como del equipo, como prueba de aceptación de los contenidos.
A3: ¿Se han definido criterios de aceptación y casos de prueba que permitan medir objetivamente el cumplimiento del requisito? | B3: Elaborar casos de Prueba para incluir en pruebas unitarias y pruebas de integración automatizadas. Establecer criterios de aceptación en formato Gherkin para alinear las expectativas del cliente con el equipo de desarrollo

Sheet RECOMENDACIONES - CU003
A1: PREGUNTA | B1: RECOMENDACIÓN
A2: ¿Se han definido criterios de aceptación y casos de prueba que permitan medir objetivamente el cumplimiento del requisito? | B2: Elaborar casos de prueba específicos, sobre todo para validar la exactitud del cálculo matemático del 12% de mora y las restricciones de archivos. Establecer criterios de aceptación para las pruebas de integración entre los diferentes sub-casos de uso.
A3: ¿Se ha definido claramente la prioridad de desarrollo para este conjunto de casos de uso? | B3: Especificar la prioridad (Alta, Media o Baja) en la descripción general de cada caso de uso
A4: ¿Se han validado y aprobado formalmente las reglas de negocio automatizadas (como la distribución de pagos y cálculos de mora)? | B4: Validar que la lógica de aplicar el pago a las deudas más antiguas y el cálculo automático del recargo del 12% reflejan exactamente el reglamento del conjunto.
